[
  {
    "name": "Minecraft",
    "votes": 10,
    "url": null,
    "user": "totemdancsir",
    "time": "04:38 PM, Jul 14"
  },
  {
    "name": "Don't Pee",
    "votes": 7,
    "url": "https://store.steampowered.com/app/2753520/Dont_Pee/",
    "user": "glassd0or",
    "time": "03:02 PM, Jul 14"
  },
  {
    "name": "Shower With your Dad Simulator",
    "votes": 4,
    "url": null,
    "user": "swinghi",
    "time": "01:55 PM, Jul 14"
  },
  {
    "name": "Visage",
    "votes": 3,
    "url": "https://store.steampowered.com/app/594330/Visage/",
    "user": "pixievixey",
    "time": "04:39 PM, Jul 14"
  },
  {
    "name": "RoadCraft",
    "votes": 3,
    "url": "https://store.steampowered.com/app/2104890/RoadCraft/",
    "user": "timelesslies",
    "time": "03:58 PM, Jul 14"
  },
  {
    "name": "RuneScape \u00ae",
    "votes": 3,
    "url": "https://store.steampowered.com/app/1343400/RuneScape/",
    "user": "trevorm0592",
    "time": "01:51 PM, Jul 14"
  },
  {
    "name": "Skin Deep",
    "votes": 2,
    "url": "https://store.steampowered.com/app/301280/Skin_Deep/",
    "user": "thethomq",
    "time": "10:46 AM, Jul 14"
  },
  {
    "name": "Solitaire",
    "votes": 2,
    "url": "https://store.steampowered.com/app/539300/Solitaire/",
    "user": "caserocker",
    "time": "01:12 PM, Jul 14"
  },
  {
    "name": "animal crossing",
    "votes": 2,
    "url": null,
    "user": "tuttutt",
    "time": "01:11 PM, Jul 14"
  },
  {
    "name": "ReMove",
    "votes": 2,
    "url": "https://store.steampowered.com/app/2789740/ReMove/",
    "user": "diluposolitaire",
    "time": "01:12 PM, Jul 14"
  },
  {
    "name": "Barbie Collector Sim 2025",
    "votes": 2,
    "url": null,
    "user": "skeifer",
    "time": "01:37 PM, Jul 14"
  },
  {
    "name": "Date Everything!",
    "votes": 2,
    "url": "https://store.steampowered.com/app/2201320/Date_Everything/",
    "user": "goose__bag",
    "time": "02:38 PM, Jul 14"
  },
  {
    "name": "Poppy",
    "votes": 2,
    "url": "https://store.steampowered.com/app/3376040/Poppy/",
    "user": "pixievixey",
    "time": "02:54 PM, Jul 14"
  },
  {
    "name": "The Forest",
    "votes": 2,
    "url": "https://store.steampowered.com/app/242760/The_Forest/",
    "user": "totemdancsir",
    "time": "03:59 PM, Jul 14"
  },
  {
    "name": "Death stranding 2",
    "votes": 2,
    "url": null,
    "user": "prosperousguard",
    "time": "03:58 PM, Jul 14"
  },
  {
    "name": "Firewatch",
    "votes": 2,
    "url": "https://store.steampowered.com/app/383870/Firewatch/",
    "user": "totemdancsir",
    "time": "04:14 PM, Jul 14"
  },
  {
    "name": "Hell's Kitchen",
    "votes": 1,
    "url": "https://store.steampowered.com/app/3833100/Hells_Kitchen/",
    "user": "rottenrobbo",
    "time": "07:41 AM, Jul 14"
  },
  {
    "name": "SULFUR",
    "votes": 1,
    "url": "https://store.steampowered.com/app/2124120/SULFUR/",
    "user": "rottenrobbo",
    "time": "07:41 AM, Jul 14"
  },
  {
    "name": "Katamari Damacy REROLL",
    "votes": 1,
    "url": "https://store.steampowered.com/app/848350/Katamari_Damacy_REROLL/",
    "user": "skeifer",
    "time": "08:18 AM, Jul 14"
  },
  {
    "name": "Bank Simulator",
    "votes": 1,
    "url": "https://store.steampowered.com/app/3355800/Bank_Simulator/",
    "user": "trevorm0592",
    "time": "01:57 PM, Jul 14"
  },
  {
    "name": "PUBG",
    "votes": 1,
    "url": null,
    "user": "murdnox",
    "time": "01:40 PM, Jul 14"
  },
  {
    "name": "PUBG: BATTLEGROUNDS",
    "votes": 1,
    "url": "https://store.steampowered.com/app/578080/PUBG_BATTLEGROUNDS/",
    "user": "caserocker",
    "time": "12:49 PM, Jul 14"
  },
  {
    "name": "PEAK",
    "votes": 1,
    "url": "https://store.steampowered.com/app/3527290/PEAK/",
    "user": "prosperousguard",
    "time": "01:06 PM, Jul 14"
  },
  {
    "name": "Left 4 Dead",
    "votes": 1,
    "url": "https://store.steampowered.com/app/500/Left_4_Dead/",
    "user": "diluposolitaire",
    "time": "01:10 PM, Jul 14"
  },
  {
    "name": "Black Mesa",
    "votes": 1,
    "url": "https://store.steampowered.com/app/362890/Black_Mesa/",
    "user": "schrombomb",
    "time": "01:17 PM, Jul 14"
  },
  {
    "name": "Jump Ship",
    "votes": 1,
    "url": "https://store.steampowered.com/app/1757300/Jump_Ship/",
    "user": "schrombomb",
    "time": "01:18 PM, Jul 14"
  },
  {
    "name": "Space Crew: Legendary Edition",
    "votes": 1,
    "url": "https://store.steampowered.com/app/1176710/Space_Crew_Legendary_Edition/",
    "user": "schrombomb",
    "time": "01:19 PM, Jul 14"
  },
  {
    "name": "Commander Keen",
    "votes": 1,
    "url": "https://store.steampowered.com/app/9180/Commander_Keen/",
    "user": "caserocker",
    "time": "01:20 PM, Jul 14"
  },
  {
    "name": "Century of Anticipation",
    "votes": 1,
    "url": "https://store.steampowered.com/app/2555760/Century_of_Anticipation/",
    "user": "diluposolitaire",
    "time": "01:20 PM, Jul 14"
  },
  {
    "name": "Satisfactory",
    "votes": 1,
    "url": "https://store.steampowered.com/app/526870/Satisfactory/",
    "user": "swinghi",
    "time": "01:24 PM, Jul 14"
  },
  {
    "name": "Genital Jousting",
    "votes": 1,
    "url": "https://store.steampowered.com/app/469820/Genital_Jousting/",
    "user": "steiner_noob",
    "time": "01:25 PM, Jul 14"
  },
  {
    "name": "There's Poop In My Soup",
    "votes": 1,
    "url": "https://store.steampowered.com/app/449540/Theres_Poop_In_My_Soup/",
    "user": "skeifer",
    "time": "01:26 PM, Jul 14"
  },
  {
    "name": "star Citizen",
    "votes": 1,
    "url": null,
    "user": "tuttutt",
    "time": "01:39 PM, Jul 14"
  },
  {
    "name": "Inscryption",
    "votes": 1,
    "url": "https://store.steampowered.com/app/1092790/Inscryption/",
    "user": "deedercakes",
    "time": "01:28 PM, Jul 14"
  },
  {
    "name": "Hypnospace Outlaw",
    "votes": 1,
    "url": "https://store.steampowered.com/app/844590/Hypnospace_Outlaw/",
    "user": "deedercakes",
    "time": "01:29 PM, Jul 14"
  },
  {
    "name": "WoW",
    "votes": 1,
    "url": null,
    "user": "murdnox",
    "time": "01:39 PM, Jul 14"
  },
  {
    "name": "Urge",
    "votes": 1,
    "url": "https://store.steampowered.com/app/1304350/Urge/",
    "user": "totempoleman",
    "time": "01:39 PM, Jul 14"
  },
  {
    "name": "Cubic Odyssey",
    "votes": 1,
    "url": "https://store.steampowered.com/app/3400000/Cubic_Odyssey/",
    "user": "bipolarbasketcase",
    "time": "01:42 PM, Jul 14"
  },
  {
    "name": "Space Engineers",
    "votes": 1,
    "url": "https://store.steampowered.com/app/244850/Space_Engineers/",
    "user": "totempoleman",
    "time": "01:42 PM, Jul 14"
  },
  {
    "name": "Warframe",
    "votes": 1,
    "url": "https://store.steampowered.com/app/230410/Warframe/",
    "user": "tankinowski",
    "time": "01:42 PM, Jul 14"
  },
  {
    "name": "RimWorld",
    "votes": 1,
    "url": "https://store.steampowered.com/app/294100/RimWorld/",
    "user": "thethomq",
    "time": "01:46 PM, Jul 14"
  },
  {
    "name": "We Harvest Shadows",
    "votes": 1,
    "url": "https://store.steampowered.com/app/1559720/We_Harvest_Shadows/",
    "user": "totempoleman",
    "time": "01:51 PM, Jul 14"
  },
  {
    "name": "The Oregon Trail",
    "votes": 1,
    "url": "https://store.steampowered.com/app/2013360/The_Oregon_Trail/",
    "user": "trevorm0592",
    "time": "01:52 PM, Jul 14"
  },
  {
    "name": "Doki Doki",
    "votes": 1,
    "url": null,
    "user": "reignfyre",
    "time": "01:53 PM, Jul 14"
  },
  {
    "name": "Abiotic Factor",
    "votes": 1,
    "url": "https://store.steampowered.com/app/427410/Abiotic_Factor/",
    "user": "bipolarbasketcase",
    "time": "01:57 PM, Jul 14"
  },
  {
    "name": "Dune: Awakening",
    "votes": 1,
    "url": "https://store.steampowered.com/app/1172710/Dune_Awakening/",
    "user": "tankinowski",
    "time": "02:36 PM, Jul 14"
  },
  {
    "name": "Terraria",
    "votes": 1,
    "url": "https://store.steampowered.com/app/105600/Terraria/",
    "user": "fapplecake",
    "time": "02:38 PM, Jul 14"
  },
  {
    "name": "PISSed Off: Peeing Simulator",
    "votes": 1,
    "url": "https://store.steampowered.com/app/3225890/PISSed_Off_Peeing_Simulator/",
    "user": "frameloss",
    "time": "02:39 PM, Jul 14"
  },
  {
    "name": "Drive Beyond Horizons",
    "votes": 1,
    "url": "https://store.steampowered.com/app/2625420/Drive_Beyond_Horizons/",
    "user": "prosperousguard",
    "time": "02:40 PM, Jul 14"
  },
  {
    "name": "F.E.A.R.",
    "votes": 1,
    "url": "https://store.steampowered.com/app/21090/FEAR/",
    "user": "shinobi681",
    "time": "02:41 PM, Jul 14"
  },
  {
    "name": "Halo CE",
    "votes": 1,
    "url": null,
    "user": "shinobi681",
    "time": "02:43 PM, Jul 14"
  },
  {
    "name": "Starcraft",
    "votes": 1,
    "url": null,
    "user": "frameloss",
    "time": "02:43 PM, Jul 14"
  },
  {
    "name": "No Man's Sky",
    "votes": 1,
    "url": "https://store.steampowered.com/app/275850/No_Mans_Sky/",
    "user": "fapplecake",
    "time": "02:52 PM, Jul 14"
  },
  {
    "name": "Grounded",
    "votes": 1,
    "url": "https://store.steampowered.com/app/962130/Grounded/",
    "user": "shinobi681",
    "time": "02:54 PM, Jul 14"
  },
  {
    "name": "Call of Cthulhu\u00ae",
    "votes": 1,
    "url": "https://store.steampowered.com/app/399810/Call_of_Cthulhu/",
    "user": "fapplecake",
    "time": "02:56 PM, Jul 14"
  },
  {
    "name": "Starbound",
    "votes": 1,
    "url": "https://store.steampowered.com/app/211820/Starbound/",
    "user": "fapplecake",
    "time": "02:56 PM, Jul 14"
  },
  {
    "name": "Path of Exile",
    "votes": 1,
    "url": "https://store.steampowered.com/app/238960/Path_of_Exile/",
    "user": "glassd0or",
    "time": "03:02 PM, Jul 14"
  },
  {
    "name": "Trombone Champ",
    "votes": 1,
    "url": "https://store.steampowered.com/app/1059990/Trombone_Champ/",
    "user": "b3njipix3l",
    "time": "03:59 PM, Jul 14"
  },
  {
    "name": "The Lord of the Rings: Return to Moria\u2122",
    "votes": 1,
    "url": "https://store.steampowered.com/app/2933130/The_Lord_of_the_Rings_Return_to_Moria/",
    "user": "totemdancsir",
    "time": "04:02 PM, Jul 14"
  },
  {
    "name": "Garbage Pail Kids: Mad Mike and the Quest for Stale Gum",
    "votes": 1,
    "url": "https://store.steampowered.com/app/1897630/Garbage_Pail_Kids_Mad_Mike_and_the_Quest_for_Stale_Gum/",
    "user": "garbagepaildood",
    "time": "04:03 PM, Jul 14"
  },
  {
    "name": "The Gold River Project",
    "votes": 1,
    "url": "https://store.steampowered.com/app/1253220/The_Gold_River_Project/",
    "user": "sr_poopiepants",
    "time": "04:39 PM, Jul 14"
  },
  {
    "name": "Kitty Cat: Jigsaw Puzzles",
    "votes": 1,
    "url": "https://store.steampowered.com/app/500580/Kitty_Cat_Jigsaw_Puzzles/",
    "user": "frameloss",
    "time": "04:40 PM, Jul 14"
  },
  {
    "name": "OpenTTD",
    "votes": 1,
    "url": "https://store.steampowered.com/app/1536610/OpenTTD/",
    "user": "tankinowski",
    "time": "05:39 AM, Jul 15"
  }
]